{
    "name": "cp2k",
    "queues": ["P_016", "P_032", "P_064", "DP_002"],
    "template": "super/cp2k.sh",
    "versions": [
        {
            "name": "7.0",
            "dir": "/work/app/CP2K/current",
            "bins": [
                {
                    "name": "cp2k.popt",
                    "path": "/work/app/CP2K/current/exe/CRAY-XC50-cce/cp2k.popt"
                }
            ]
        },
        {
            "name": "8.1.0",
            "dir": "/work/app/CP2K/cp2k-8.1.0",
            "bins": [
                {
                    "name": "cp2k.popt",
                    "path": "/work/app/CP2K/cp2k-8.1.0/exe/CRAY-XC50_gnu/cp2k.popt"
                }
            ]
        },
        {
            "name": "8.2.0",
            "dir": "/work/app/CP2K/cp2k-8.2.0",
            "bins": [
                {
                    "name": "cp2k.popt",
                    "path": "/work/app/CP2K/cp2k-8.2.0/exe/CRAY-XC50_gnu/cp2k.popt"
                }
            ]
        },
        {
            "name": "9.1.0",
            "dir": "/work/app/CP2K/cp2k-9.1.0",
            "bins": [
                {
                    "name": "cp2k.popt",
                    "path": "/work/app/CP2K/cp2k-9.1.0/exe/CRAY-XC50-gnu/cp2k.popt"
                }
            ]
        },
        {
            "name": "2022.1",
            "dir": "/work/app/CP2K/cp2k-2022.1",
            "bins": [
                {
                    "name": "cp2k.popt",
                    "path": "/work/app/CP2K/cp2k-2022.1/exe/CRAY-XC50-gnu/cp2k.popt"
                }
            ]
        },
        {
            "name": "2023.1",
            "dir": "/work/app/CP2K/cp2k-2023.1",
            "bins": [
                {
                    "name": "cp2k.popt",
                    "path": "/work/app/CP2K/cp2k-2023.1/exe/CRAY-XC50-gnu/cp2k.popt"
                }
            ]
        }
    ]
}
